flask_saestorage.py
Flask_SaeStorage-0.9.0.dist-info/DESCRIPTION.rst
Flask_SaeStorage-0.9.0.dist-info/METADATA
Flask_SaeStorage-0.9.0.dist-info/metadata.json
Flask_SaeStorage-0.9.0.dist-info/RECORD
Flask_SaeStorage-0.9.0.dist-info/top_level.txt
Flask_SaeStorage-0.9.0.dist-info/WHEEL
