Metadata-Version: 1.1
Name: Flask-SaeStorage
Version: 0.9.0
Summary: SAE Storage for Flask
Home-page: https://github.com/csuzhangxc/Flask-SaeStorage
Author: Zhang Xuecheng
Author-email: csuzhangxc@gmail.com
License: MIT
Keywords: sae storage for flask
Platform: any
Classifier: Development Status :: 4 - Beta
Classifier: Environment :: Web Environment
Classifier: Intended Audience :: Developers
Classifier: License :: OSI Approved :: MIT License
Classifier: Operating System :: OS Independent
Classifier: Programming Language :: Python
Classifier: Topic :: Internet :: WWW/HTTP :: Dynamic Content
Classifier: Topic :: Software Development :: Libraries :: Python Modules
